repoflow-1.0.0.dist-info/licenses/LICENSE
src/__init__.py
src/config_manager.py
src/docker_manager.py
src/git_manager.py
src/github_manager.py
src/pipeline_generator.py
src/project_detector.py
src/pypi_manager.py
src/secret_scanner.py
tests/__init__.py
repoflow-1.0.0.dist-info/METADATA
repoflow-1.0.0.dist-info/WHEEL
repoflow-1.0.0.dist-info/entry_points.txt
repoflow-1.0.0.dist-info/top_level.txt
repoflow-1.0.0.dist-info/RECORD
