Metadata-Version: 2.4
Name: repoflow
Version: 1.0.0
Summary: 自动化项目发布工具 - 简化从本地到GitHub的完整流程
Home-page: https://github.com/BACH-AI-Tools/RepoFlow
Author: BACH-AI-Tools
Author-email: 
License: MIT
Project-URL: Homepage, https://github.com/BACH-AI-Tools/RepoFlow
Project-URL: Bug Reports, https://github.com/BACH-AI-Tools/RepoFlow/issues
Project-URL: Source, https://github.com/BACH-AI-Tools/RepoFlow
Keywords: automation,github,cicd,docker,npm,pypi,deployment
Classifier: Development Status :: 4 - Beta
Classifier: Intended Audience :: Developers
Classifier: Topic :: Software Development :: Build Tools
Classifier: License :: OSI Approved :: MIT License
Classifier: Programming Language :: Python :: 3
Classifier: Programming Language :: Python :: 3.8
Classifier: Programming Language :: Python :: 3.9
Classifier: Programming Language :: Python :: 3.10
Classifier: Programming Language :: Python :: 3.11
Classifier: Operating System :: OS Independent
Requires-Python: >=3.8
License-File: LICENSE
Requires-Dist: requests>=2.31.0
Requires-Dist: PyGithub>=2.1.1
Requires-Dist: GitPython>=3.1.40
Requires-Dist: python-dotenv>=1.0.0
Requires-Dist: click>=8.1.7
Requires-Dist: rich>=13.7.0
Requires-Dist: pyyaml>=6.0.1
Provides-Extra: dev
Requires-Dist: pytest>=7.0.0; extra == "dev"
Requires-Dist: black>=23.0.0; extra == "dev"
Requires-Dist: flake8>=6.0.0; extra == "dev"
Requires-Dist: mypy>=1.0.0; extra == "dev"
Dynamic: home-page
Dynamic: license-file
Dynamic: requires-python
